usmerge/__init__.py
usmerge/usmerge.py
usmerge-0.2.1.dist-info/LICENSE
usmerge-0.2.1.dist-info/METADATA
usmerge-0.2.1.dist-info/WHEEL
usmerge-0.2.1.dist-info/top_level.txt
usmerge-0.2.1.dist-info/RECORD
