Metadata-Version: 2.1
Name: usmerge
Version: 0.2.1
Summary: A simple package to merge one-dimension data by unsupervised method
Home-page: https://github.com/wanghui5801/usmerge
Author: HuiWang
Author-email: huiw1128@gmail.com
Classifier: Development Status :: 3 - Alpha
Classifier: Intended Audience :: Developers
Classifier: License :: OSI Approved :: MIT License
Classifier: Programming Language :: Python :: 3
Classifier: Programming Language :: Python :: 3.6
Classifier: Programming Language :: Python :: 3.7
Classifier: Programming Language :: Python :: 3.8
Classifier: Programming Language :: Python :: 3.9
License-File: LICENSE
Requires-Dist: pandas>=1.0.0
Requires-Dist: numpy>=1.18.0
